autograd/__init__.py
autograd/dependency.py
autograd/engin.py
autograd/math_operations.py
autograd/node.py
autograd/parameter.py
autograd/tensor.py
autograd/tensor_modifications.py
deprecated/__init__.py
deprecated/autogradgpu/__init__.py
deprecated/autogradgpu/dependency.py
deprecated/autogradgpu/engin.py
deprecated/autogradgpu/math_operations.py
deprecated/autogradgpu/node.py
deprecated/autogradgpu/parameter.py
deprecated/autogradgpu/tensor.py
deprecated/autogradgpu/tensor_modifications.py
deprecated/metal/__init__.py
deprecated/metal/functions.py
deprecated/metal/loss_functions.py
deprecated/metal/module.py
deprecated/metal/nn.py
deprecated/metal/optimizers.py
deprecated/metal/layers/__init__.py
deprecated/metal/layers/activation_functions.py
deprecated/metal/layers/averagepooling.py
deprecated/metal/layers/batchnormalization_.py
deprecated/metal/layers/conv2D.py
deprecated/metal/layers/dense.py
deprecated/metal/layers/dropout.py
deprecated/metal/layers/flatten.py
deprecated/metal/layers/layer.py
deprecated/metal/layers/maxpooling.py
deprecated/metal/models/__init__.py
deprecated/metal/models/convnet.py
deprecated/metal/utils/__init__.py
deprecated/metal/utils/data_manipulation.py
deprecated/metal/utils/data_operation.py
deprecated/metal/utils/layer_data_manipulations.py
deprecated/metal/utils/misc.py
deprecated/metal/utils/production_util.py
deprecated/metal/utils/data_loader/__init__.py
deprecated/metal/utils/data_loader/data_loader.py
deprecated/metal/utils/data_loader/extract.py
deprecated/metalgpu/__init__.py
deprecated/metalgpu/functions.py
deprecated/metalgpu/loss_functions.py
deprecated/metalgpu/module.py
deprecated/metalgpu/nn.py
deprecated/metalgpu/optimizers.py
deprecated/metalgpu/layers/__init__.py
deprecated/metalgpu/layers/activation_functions.py
deprecated/metalgpu/layers/averagepooling.py
deprecated/metalgpu/layers/batchnormalization_.py
deprecated/metalgpu/layers/conv2D.py
deprecated/metalgpu/layers/dense.py
deprecated/metalgpu/layers/dropout.py
fullmetal-0.59.dist-info/METADATA
fullmetal-0.59.dist-info/WHEEL
fullmetal-0.59.dist-info/top_level.txt
fullmetal-0.59.dist-info/RECORD
