Metadata-Version: 2.1
Name: fullmetal
Version: 0.59
Summary: Deep Learning project
Home-page: UNKNOWN
Author: Miguel Myers
Author-email: miguelmyers8@gmail.com
License: UNKNOWN
Platform: UNKNOWN
Requires-Dist: six (>=1.10.0)
